MANIFEST.in
README.txt
hipchatpy.py
requirements.txt
setup.py
hipchatpy.egg-info/PKG-INFO
hipchatpy.egg-info/SOURCES.txt
hipchatpy.egg-info/dependency_links.txt
hipchatpy.egg-info/entry_points.txt
hipchatpy.egg-info/requires.txt
hipchatpy.egg-info/top_level.txt