Metadata-Version: 1.1
Name: hipchatpy
Version: 0.1.4
Summary: Simple HipChat client library
Home-page: https://github.com/iktakahiro/hipchatpy
Author: Takahiro Ikeuchi
Author-email: takahiro.ikeuchi@gmail.com
License: MIT
Keywords: HipChat,HipChat Client
Platform: UNKNOWN
Classifier: License :: OSI Approved :: MIT License
Classifier: Programming Language :: Python :: 3.4
Classifier: Topic :: System :: Logging
Classifier: Topic :: Communications :: Chat
